<?xml version="1.0" encoding="ISO-8859-1" standalone="yes"?>
<TileDesigns>
	<DataChecksum NoParse="1">
		<Ignore>DisplayName</Ignore>
		<Translate>DisplayName</Translate>
	</DataChecksum>
	<TileDesign InternalName="WindShrine_02">
		<DisplayName>WindShrine_02</DisplayName>
		<Thumbnail>\Game\Gfx\tile_icon.png</Thumbnail>
		<DecalName>Gfx\Decals\GenericGrass_Decal.dds</DecalName>
		<LowResShadow>WindShrine_02_shadow.png</LowResShadow>
		<HighResShadow>WindShrine_02_shadow.png</HighResShadow>
		<ShadowTransparency>50</ShadowTransparency>
		<IsCore>0</IsCore>
		<IsHiddenFromEditor>0</IsHiddenFromEditor>
		<SubTileFlags>1</SubTileFlags>
		<TileDesignObject InternalName="_obj0">
			<ObjectType>PropModelType</ObjectType>
			<ObjectDefName>S_Air_Pillar01</ObjectDefName>
			<ObjectLOD>1</ObjectLOD>
			<IgnoreTerrain>0</IgnoreTerrain>
			<Position>2.500000,36.000000,0.000000</Position>
			<Rotation>-3.141593,0.000000,0.000000</Rotation>
			<RotationSpeed>0.000000,0.000000,0.000000</RotationSpeed>
			<Scale>1.0000</Scale>
			<BaseScale>1.0000</BaseScale>
		</TileDesignObject>
		<TileDesignObject InternalName="_obj1">
			<ObjectType>PropModelType</ObjectType>
			<ObjectDefName>S_Air_Pillar01</ObjectDefName>
			<ObjectLOD>1</ObjectLOD>
			<IgnoreTerrain>0</IgnoreTerrain>
			<Position>-2.500000,36.000000,0.000000</Position>
			<Rotation>-3.141593,-3.150001,0.000000</Rotation>
			<RotationSpeed>0.000000,0.000000,0.000000</RotationSpeed>
			<Scale>1.0000</Scale>
			<BaseScale>1.0000</BaseScale>
		</TileDesignObject>
		<TileDesignObject InternalName="_obj2">
			<ObjectType>PropModelType</ObjectType>
			<ObjectDefName>S_Air_Pillar01</ObjectDefName>
			<ObjectLOD>1</ObjectLOD>
			<IgnoreTerrain>0</IgnoreTerrain>
			<Position>0.000000,36.000000,-3.500000</Position>
			<Rotation>-3.141593,-4.725000,0.000000</Rotation>
			<RotationSpeed>0.000000,0.000000,0.000000</RotationSpeed>
			<Scale>1.0000</Scale>
			<BaseScale>1.0000</BaseScale>
		</TileDesignObject>
		<TileDesignObject InternalName="_obj3">
			<ObjectType>PropModelType</ObjectType>
			<ObjectDefName>S_Air_Pillar01</ObjectDefName>
			<ObjectLOD>1</ObjectLOD>
			<IgnoreTerrain>0</IgnoreTerrain>
			<Position>0.000000,36.000000,3.500000</Position>
			<Rotation>-3.141593,-7.874997,0.000000</Rotation>
			<RotationSpeed>0.000000,0.000000,0.000000</RotationSpeed>
			<Scale>1.0000</Scale>
			<BaseScale>1.0000</BaseScale>
		</TileDesignObject>
		<TileDesignObject InternalName="_obj4">
			<ObjectType>PropModelType</ObjectType>
			<ObjectDefName>S_Air_Pillar01</ObjectDefName>
			<ObjectLOD>1</ObjectLOD>
			<IgnoreTerrain>0</IgnoreTerrain>
			<Position>0.000000,0.000000,17.000000</Position>
			<Rotation>0.000000,-1.575000,0.000000</Rotation>
			<RotationSpeed>0.000000,0.000000,0.000000</RotationSpeed>
			<Scale>0.7200</Scale>
			<BaseScale>1.0000</BaseScale>
		</TileDesignObject>
		<TileDesignObject InternalName="_obj5">
			<ObjectType>PropModelType</ObjectType>
			<ObjectDefName>S_Air_Pillar01</ObjectDefName>
			<ObjectLOD>1</ObjectLOD>
			<IgnoreTerrain>0</IgnoreTerrain>
			<Position>-16.000000,0.000000,0.000000</Position>
			<Rotation>0.000000,-3.150001,0.000000</Rotation>
			<RotationSpeed>0.000000,0.000000,0.000000</RotationSpeed>
			<Scale>0.7200</Scale>
			<BaseScale>1.0000</BaseScale>
		</TileDesignObject>
		<TileDesignObject InternalName="_obj6">
			<ObjectType>PropModelType</ObjectType>
			<ObjectDefName>S_Air_Pillar01</ObjectDefName>
			<ObjectLOD>1</ObjectLOD>
			<IgnoreTerrain>0</IgnoreTerrain>
			<Position>0.000000,0.000000,-17.000000</Position>
			<Rotation>0.000000,-4.725000,0.000000</Rotation>
			<RotationSpeed>0.000000,0.000000,0.000000</RotationSpeed>
			<Scale>0.7200</Scale>
			<BaseScale>1.0000</BaseScale>
		</TileDesignObject>
		<TileDesignObject InternalName="_obj7">
			<ObjectType>PropModelType</ObjectType>
			<ObjectDefName>S_Air_Pillar01</ObjectDefName>
			<ObjectLOD>1</ObjectLOD>
			<IgnoreTerrain>0</IgnoreTerrain>
			<Position>16.000000,1.000000,0.000000</Position>
			<Rotation>0.000000,-6.299997,0.000000</Rotation>
			<RotationSpeed>0.000000,0.000000,0.000000</RotationSpeed>
			<Scale>0.6800</Scale>
			<BaseScale>1.0000</BaseScale>
		</TileDesignObject>
		<TileDesignObject InternalName="_obj8">
			<ObjectType>PropModelType</ObjectType>
			<ObjectDefName>Statue_FallenGuard1</ObjectDefName>
			<ObjectLOD>5</ObjectLOD>
			<IgnoreTerrain>0</IgnoreTerrain>
			<Position>-12.739691,0.000000,17.475540</Position>
			<Rotation>0.000000,0.000000,0.000000</Rotation>
			<RotationSpeed>0.000000,0.000000,0.000000</RotationSpeed>
			<Scale>0.5000</Scale>
			<BaseScale>1.0000</BaseScale>
		</TileDesignObject>
		<TileDesignObject InternalName="_obj9">
			<ObjectType>PropModelType</ObjectType>
			<ObjectDefName>Statue_FallenGuard1</ObjectDefName>
			<ObjectLOD>5</ObjectLOD>
			<IgnoreTerrain>0</IgnoreTerrain>
			<Position>14.643764,0.000000,16.462906</Position>
			<Rotation>0.000000,0.000000,0.000000</Rotation>
			<RotationSpeed>0.000000,0.000000,0.000000</RotationSpeed>
			<Scale>0.5000</Scale>
			<BaseScale>1.0000</BaseScale>
		</TileDesignObject>
		<TileDesignObject InternalName="_obj10">
			<ObjectType>PropModelType</ObjectType>
			<ObjectDefName>Statue_FallenGuard1</ObjectDefName>
			<ObjectLOD>5</ObjectLOD>
			<IgnoreTerrain>0</IgnoreTerrain>
			<Position>14.659271,0.000000,-14.903915</Position>
			<Rotation>0.000000,0.000000,0.000000</Rotation>
			<RotationSpeed>0.000000,0.000000,0.000000</RotationSpeed>
			<Scale>0.5000</Scale>
			<BaseScale>1.0000</BaseScale>
		</TileDesignObject>
		<TileDesignObject InternalName="_obj11">
			<ObjectType>PropModelType</ObjectType>
			<ObjectDefName>Statue_FallenGuard1</ObjectDefName>
			<ObjectLOD>5</ObjectLOD>
			<IgnoreTerrain>0</IgnoreTerrain>
			<Position>-11.995285,0.000000,-15.413101</Position>
			<Rotation>0.000000,0.000000,0.000000</Rotation>
			<RotationSpeed>0.000000,0.000000,0.000000</RotationSpeed>
			<Scale>0.5000</Scale>
			<BaseScale>1.0000</BaseScale>
		</TileDesignObject>
		<TileDesignPath InternalName="_path0"/>
		<TileDesignPath InternalName="_path1"/>
		<TileDesignPath InternalName="_path2"/>
	</TileDesign>
</TileDesigns>
